gravityspy/__init__.py
gravityspy/_version.py
gravityspy/api/__init__.py
gravityspy/api/project.py
gravityspy/classify/__init__.py
gravityspy/classify/classify.py
gravityspy/ml/GS_utils.py
gravityspy/ml/__init__.py
gravityspy/ml/labelling_test_glitches.py
gravityspy/ml/read_image.py
gravityspy/ml/train_classifier.py
gravityspy/ml/train_semantic_index.py
gravityspy/plot/__init__.py
gravityspy/plot/plot.py
gravityspy/table/__init__.py
gravityspy/table/events.py
gravityspy/utils/__init__.py
gravityspy/utils/log.py
gravityspy/utils/utils.py
gravityspy-1.0.1.data/scripts/filter_psql
gravityspy-1.0.1.data/scripts/gettriggers
gravityspy-1.0.1.data/scripts/gravityspyDBs
gravityspy-1.0.1.data/scripts/gspysearch
gravityspy-1.0.1.data/scripts/modify_subject
gravityspy-1.0.1.data/scripts/parse_classifications
gravityspy-1.0.1.data/scripts/promote_users
gravityspy-1.0.1.data/scripts/retireimages
gravityspy-1.0.1.data/scripts/retrain_model_and_relabel_images
gravityspy-1.0.1.data/scripts/run_hveto.sh
gravityspy-1.0.1.data/scripts/setup_update_scores
gravityspy-1.0.1.data/scripts/train_similarity_model
gravityspy-1.0.1.data/scripts/trainingset_psql
gravityspy-1.0.1.data/scripts/trainmodel
gravityspy-1.0.1.data/scripts/updateSite
gravityspy-1.0.1.data/scripts/update_similarity_score
gravityspy-1.0.1.data/scripts/updatescores
gravityspy-1.0.1.data/scripts/upload
gravityspy-1.0.1.data/scripts/wscan
gravityspy-1.0.1.dist-info/LICENSE
gravityspy-1.0.1.dist-info/METADATA
gravityspy-1.0.1.dist-info/WHEEL
gravityspy-1.0.1.dist-info/top_level.txt
gravityspy-1.0.1.dist-info/RECORD
